g3tables/__init__.py
g3tables/py.typed
g3tables/plc_composition_io_table/__init__.py
g3tables/plc_composition_io_table/_extend_table.py
g3tables/plc_composition_io_table/_table.py
g3tables/plc_composition_io_table/io_signals.json
g3tables/sw_definition_table/__init__.py
g3tables/sw_definition_table/_table.py
g3tables/system_config/__init__.py
g3tables/system_config/_cli.py
g3tables/system_config/_g3core_updater.py
g3tables/system_config/_hw_connections.py
g3tables/system_config/_iomap_updater.py
g3tables/system_config/_logger.py
g3tables/system_config/_sw_system_dict_wrapper.py
g3tables/system_config/_system_config_processor.py
g3tables/system_config/type_hinting.py
g3tables/utils/__init__.py
g3tables/utils/_d2nd.py
g3tables/utils/_interval.py
g3tables/utils/gdrive/__init__.py
g3tables/utils/gdrive/_gdrive.py
g3tables/utils/gdrive/_update_creds.py
g3tables/visualization_table/__init__.py
g3tables/visualization_table/_table.py
g3tables-0.2.16.dist-info/licenses/LICENCE
g3tables-0.2.16.dist-info/METADATA
g3tables-0.2.16.dist-info/WHEEL
g3tables-0.2.16.dist-info/entry_points.txt
g3tables-0.2.16.dist-info/top_level.txt
g3tables-0.2.16.dist-info/RECORD
